plumiftp
