Metadata-Version: 1.0
Name: plumiftp
Version: 0.4
Summary: resumable large video FTP uploads, wrapped around Zope FTP server
Home-page: http://plumi.org/
Author: Andy Nicholson
Author-email: andy@engagemedia.org
License: GPLv3
Keywords: video zope plone ftp
Platform: UNKNOWN
